mpvis/__init__.py
mpvis/log_formatter.py
mpvis/mddrt/__init__.py
mpvis/mddrt/actions.py
mpvis/mddrt/drt_parameters.py
mpvis/mddrt/pruning.py
mpvis/mddrt/tree_builder.py
mpvis/mddrt/tree_diagrammer.py
mpvis/mddrt/tree_grouper.py
mpvis/mddrt/tree_node.py
mpvis/mddrt/utils/__init__.py
mpvis/mddrt/utils/actions.py
mpvis/mddrt/utils/builder.py
mpvis/mddrt/utils/color_schemes.py
mpvis/mddrt/utils/constants.py
mpvis/mddrt/utils/diagrammer.py
mpvis/mddrt/utils/misc.py
mpvis/mddrt/utils/optional_activities.py
mpvis/mpdfg/__init__.py
mpvis/mpdfg/actions.py
mpvis/mpdfg/dfg.py
mpvis/mpdfg/dfg_builder.py
mpvis/mpdfg/dfg_parameters.py
mpvis/mpdfg/diagrammers/graphviz.py
mpvis/mpdfg/diagrammers/mermaid.py
mpvis/mpdfg/utils/__init__.py
mpvis/mpdfg/utils/actions.py
mpvis/mpdfg/utils/builder.py
mpvis/mpdfg/utils/color_scales.py
mpvis/mpdfg/utils/constants.py
mpvis/mpdfg/utils/diagrammer.py
mpvis/mpdfg/utils/filters.py
mpvis/preprocessing/__init__.py
mpvis/preprocessing/log_variant_pruning.py
mpvis/preprocessing/manual_log_grouping.py
mpvis-1.0.5.dist-info/METADATA
mpvis-1.0.5.dist-info/WHEEL
mpvis-1.0.5.dist-info/licenses/LICENSE
mpvis-1.0.5.dist-info/RECORD
