Metadata-Version: 2.4
Name: mpvis
Version: 1.0.5
Summary: Package for Multi-Perspective Process Visualization
Project-URL: Homepage, https://github.com/nicoabarca/mpvis
Project-URL: Issues, https://github.com/nicoabarca/mpvis/issues
License:                     GNU AFFERO GENERAL PUBLIC LICENSE
License-File: LICENSE
Classifier: Intended Audience :: Developers
Classifier: Intended Audience :: Science/Research
Classifier: Operating System :: OS Independent
Classifier: Programming Language :: Python :: 3
Classifier: Topic :: Scientific/Engineering :: Visualization
Requires-Python: >=3.9
Requires-Dist: graphviz
Requires-Dist: numpy
Requires-Dist: pandas
Requires-Dist: pm4py
Requires-Dist: pyarrow
Requires-Dist: tqdm
